<vector xmlns:android="http://schemas.android.com/apk/res/android" xmlns:aapt="http://schemas.android.com/aapt" android:width="3459dp" android:height="3487dp" android:viewportWidth="3459" android:viewportHeight="3487">
    <group>
        <clip-path android:pathData="M0 0h3458.4v3486.6H0z"/>
        <path android:pathData="M1460.3 2155.2c18 11.7 36.7 22.3 56.1 31.5 19.4 9.3 39.3 17.3 59.8 24l-152.1 466.6c-40.9-13.3-80.7-29.4-119.3-47.8-38.7-18.6-76.2-39.6-112.1-63l267.6-411.3zm1092.2 123.6c-23.3 35.9-49.1 70.2-77 102.9l-372.8-319c13.9-16.4 26.8-33.6 38.5-51.5l411.3 267.6zm63-112.2c-18.6 38.7-39.6 76.2-63 112.2l-411.3-267.7c11.7-17.9 22.3-36.7 31.5-56.1l442.8 211.6zm-1292.7-145.4c12.2 17.7 25.5 34.6 39.8 50.5l-365 328.1c-28.6-31.7-55.2-65.4-79.5-101l404.7-277.6zm1385.9-354.8c3.4 43.3 3.9 86.2 1.6 128.6l-490-26.1c1.1-21.2 0.8-42.7-0.9-64.4l489.3-38.1zm-1461.5 178.2l481.5-101.9-464.1 163.9L801.8 2070c-14-39.9-25.7-81.2-34.7-123.8l480.1-101.6zm11.7 45c0.4 1.2 0.8 2.5 1.2 3.8-0.4-1.3-0.8-2.6-1.2-3.8zm-3.4-11.4c0.2 0.6 0.4 1.2 0.5 1.8-0.1-0.6-0.3-1.2-0.5-1.8zm-4.7-17.7c0.7 2.6 1.3 5.2 2 7.8-0.3-1.3-0.7-2.6-1-3.9-0.3-1.3-0.7-2.6-1-3.9zm-13.7-144c1.2-21.6 3.7-42.9 7.6-63.9l484 90.1-491.6-26.2c-1.1 21.3-0.8 42.8 0.9 64.4L748.7 1819c-3.4-43.2-3.9-86.2-1.6-128.6l490 26.1zm1418.5-301.1c14 40 25.7 81.3 34.7 123.8l-480.1 101.6c-4.5-21.3-10.3-42-17.4-62l462.8-163.4zm-116.3-228.8c24.1 35.1 46.1 72.1 65.7 110.6l-437.5 222.4c-9.8-19.3-20.8-37.8-32.9-55.4l404.7-277.6zm-1254.6 343.8c-9.3 19.4-17.3 39.3-24 59.8-6.6 20.3-12 41.2-15.9 62.4l-482.5-89.8c7.9-42.5 18.5-84.1 31.8-124.7 13.3-40.8 29.4-80.7 47.9-119.3l442.7 211.6zm748.6-722.3c40.9 13.3 80.7 29.4 119.3 47.9 38.7 18.5 76.2 39.5 112.2 62.9l-267.7 411.3c-18-11.7-36.7-22.2-56.1-31.5s-39.3-17.3-59.8-24l152.1-466.6zm-678.6 614.6v0.1c-13.9 16.3-26.9 33.5-38.5 51.5l-411.4-267.6c23.4-36 49.2-70.3 77.1-103l372.8 319zm95.5-85.9c-17.8 12.2-34.7 25.5-50.5 39.8l-328.1-365c31.7-28.6 65.4-55.1 101-79.5l277.6 404.7zm202.2-574.1c43.3-3.4 86.2-3.9 128.6-1.7l-26.1 490.1c-21.2-1.1-42.8-0.9-64.4 0.8l-38.1-489.2zm-127.2 18.4c42.6-9 85-15 127.2-18.4l38.1 489.3c-21.1 1.6-42.4 4.7-63.7 9.2l-101.6-480.1z" android:fillAlpha="0.1">
            <aapt:attr name="android:fillColor">
                <gradient android:centerX="1727.8" android:centerY="1744.4" android:gradientRadius="981.4" android:type="radial">
                    <item android:offset="0.5" android:color="#00FFFFFF"/>
                    <item android:offset="1" android:color="#FFFFFFFF"/>
                </gradient>
            </aapt:attr>
        </path>
        <path android:pathData="M1316.2 1474.3l-411.3-267.6c-23.4 35.9-44.4 73.4-62.9 112.1l442.7 211.6c9.3-19.3 19.8-38.1 31.5-56.1zm-71.4 178.3l-482.6-89.8c-7.8 41.8-12.9 84.5-15.2 127.6l490.1 26.1c1.2-21.6 3.7-42.9 7.7-63.9zm163.9 464.1l-319 372.8c32.7 27.9 67 53.7 102.9 77l267.7-411.3c-18-11.7-35.2-24.6-51.6-38.5zm758.8-597.1c-9.8-19.3-20.8-37.8-32.9-55.4l-405.9 278.5 438.8-223.1z" android:fillColor="#ffffff" android:fillAlpha="0.15"/>
        <path android:pathData="M1728.7 1742.7l152.5-468c-20.3-6.7-41.1-12-62.4-16l-90.1 484z" android:fillColor="#ffffff" android:fillAlpha="0.15"/>
        <path android:pathData="M1728.7 1742.7l90.1-483.9c-21-3.9-42.3-6.5-63.9-7.6l-26.2 491.5zm366.1-329c-14.4-16.1-29.8-31-46.2-45l-319.9 374 366.1-329.1v0.1z" android:fillColor="#ffffff" android:fillAlpha="0.15"/>
        <path android:pathData="M1728.7 1742.7l405.9-278.5c-12.2-17.7-25.5-34.6-39.8-50.5l-366.1 329z" android:fillColor="#ffffff" android:fillAlpha="0.15"/>
        <path android:pathData="M1728.7 1742.7l481.5-101.9c-4.5-21.3-10.3-42-17.4-62l-464.1 163.9z" android:fillColor="#ffffff" android:fillAlpha="0.15"/>
        <path android:pathData="M1728.7 1742.7l223.1 438.8c19.3-9.8 37.8-20.8 55.4-32.9l-278.5-405.9zm163.9 464.1c20.5-7.2 40.2-15.6 59.2-25.3l-223.1-438.8 163.9 464.1zm-163.9-464.1l-152.5 468c20.3 6.7 41.2 12 62.4 16l90.1-484zm0 0l38.2 490.7c21.1-1.6 42.4-4.7 63.7-9.2l-101.9-481.5z" android:fillColor="#ffffff" android:fillAlpha="0.15"/>
        <path android:pathData="M1728.7 1742.7l491.6 26.2c1.1-21.3 0.8-42.7-0.9-64.4l-490.7 38.2zm374 320c13.9-16.4 26.8-33.6 38.5-51.5l-412.4-268.4 373.9 319.9zm-374-320l-444-212.3c-9.3 19.4-17.3 39.3-24 59.8l468 152.5zm-412.5-268.4c-11.7 18-22.2 36.8-31.5 56.1l444 212.3-412.5-268.4z" android:fillColor="#ffffff" android:fillAlpha="0.15"/>
        <path android:pathData="M1728.7 1742.7l-374-320c-13.9 16.4-26.8 33.6-38.5 51.6l412.5 268.4zm0 0l-468-152.5c-6.6 20.3-12 41.2-15.9 62.4l483.9 90.1zm0 0l-319.9 374c16.3 13.9 33.5 26.8 51.5 38.5l268.4-412.5zm0 0l-490.7 38.2c1.6 21.1 4.7 42.4 9.2 63.7l481.5-101.9z" android:fillColor="#ffffff" android:fillAlpha="0.15"/>
        <path android:pathData="M1728.7 1742.7l-491.5-26.2c-1.2 21.3-0.9 42.8 0.8 64.4l490.7-38.2zm-1122-959.9c-41.9 49-80.5 100.7-115.6 154.6-35.1 54-66.7 110.3-94.6 168.5L842 1318.8c18.5-38.7 39.5-76.2 62.9-112.1 23.4-35.9 49.1-70.3 77-103L606.7 782.8zM2605 1297.2l440.3-223.8c-29.4-57.9-62.4-113.4-98.7-166.2l-407.2 279.4c24.1 35.1 46 72.1 65.6 110.6zm85.3 242l483-102.2c-13.6-63.9-31-126-52.2-186l-465.5 164.4c14 40 25.7 81.3 34.7 123.8zm-150.9-352.6l407.2-279.4c-36.7-53.3-76.6-104-119.5-151.7l-367.3 330.1c28.6 31.7 55.2 65.5 79.6 101zM1805 2722.7l38.3 492.2c63.4-5 127.2-14.1 191.1-27.7l-102.2-482.9c-42.5 9-85 15-127.2 18.4zm670.5-341l375.2 320.9c41.9-49 80.5-100.7 115.6-154.6l-413.8-269.2c-23.3 35.9-49.1 70.2-77 102.8v0.1zM2056 2669.6l164.4 465.5c61.5-21.6 120.7-47 177.6-75.9L2174.2 2619c-37.8 19.2-77.3 36.2-118.2 50.5v0.1z" android:fillColor="#ffffff" android:fillAlpha="0.15"/>
        <path android:pathData="M2564.2 2960.6c-52.8 36.3-108.2 69.3-166.2 98.7L2174.2 2619c38.6-19.6 75.5-41.5 110.7-65.6l279.3 407.2zm-1140.1-283.3c40.6 13.3 82.2 23.9 124.6 31.9l-90.4 485.4c-63.6-11.8-126.2-27.9-187.2-47.8l153-469.5zm-334.3-187.8c32.6 27.9 67 53.7 102.9 77v0.1c35.9 23.4 73.4 44.3 112.1 62.9L1091.9 3075c-58.2-27.9-114.4-59.5-168.4-94.6-54-35.2-105.7-73.8-154.7-115.7l321-375.2zm334.3 187.8zM918 2298.8c24.4 35.5 51 69.3 79.6 101l-367.2 330.1c-43-47.7-82.9-98.3-119.6-151.7L918 2298.9v-0.1zm2282.9-670.7c5.2 65 6 129.5 2.6 193.2l-493.1-26.3c2.2-42.4 1.7-85.4-1.7-128.6l492.2-38.3zM842 1318.8c-18.5 38.6-34.5 78.4-47.9 119.3-13.3 40.6-23.9 82.2-31.8 124.6-7.8 41.9-13 84.5-15.2 127.7-2.3 42.4-1.8 85.4 1.6 128.6 3.4 42.2 9.4 84.7 18.4 127.2 9 42.5 20.7 83.9 34.7 123.8l-465.5 164.4c-21.1-60-38.6-122.1-52.1-186-13.6-63.9-22.7-127.7-27.7-191.1-5.2-64.9-6-129.4-2.6-193.2 3.4-64.8 11.1-128.9 22.9-191.8 11.8-63.6 27.9-126.2 47.8-187.2 20.1-61.4 44.1-121.3 71.9-179.2v-0.1l445.5 213zm1846.7-698.1c48.9 41.8 95.1 86.8 138.4 134.8l-367.3 330.1-365 328.1c-14.4-16.1-29.8-31-46.1-45l319-372.8 321-375.2zM1423 298.2c63.9-13.6 127.7-22.7 191.1-27.7 65-5.2 129.5-6 193.2-2.6 64.8 3.4 128.9 11.1 191.8 22.9 63.7 11.8 126.2 27.9 187.2 47.8 61.5 20.1 121.3 44.1 179.3 71.9l-213 445.5c-38.6-18.5-78.4-34.5-119.3-47.9-40.6-13.3-82.2-23.9-124.6-31.8-41.9-7.8-84.5-13-127.7-15.2-42.4-2.3-85.4-1.8-128.6 1.6-42.2 3.4-84.6 9.4-127.2 18.4L1423 298.2zm93.4 1888.5c-19.3-9.2-38.1-19.7-56.1-31.5l268.4-412.5-212.3 444zm-153.8-115c-14.3-15.9-27.6-32.8-39.8-50.5l405.9-278.5-366.1 329zm366.1-329v-0.1 0.1zm0-0.1l-329-366c15.9-14.3 32.8-27.6 50.5-39.8l278.5 405.8zm38.2 490.8c21.1-1.6 42.4-4.7 63.7-9.2l101.6 480.1c-42.5 9-85 15.1-127.2 18.4l-38.1-489.3zm693.3-1147.5c28.6 31.7 55.2 65.4 79.6 101l-404.7 277.6c-12.2-17.8-25.6-34.7-39.9-50.6l365-328z" android:strokeAlpha="0.25" android:fillAlpha="0.25">
            <aapt:attr name="android:fillColor">
                <gradient android:centerX="1717.4" android:centerY="1719.4" android:gradientRadius="1451.4" android:type="radial">
                    <item android:offset="0.7" android:color="#00FFFFFF"/>
                    <item android:offset="1" android:color="#7FFFFFFF"/>
                </gradient>
            </aapt:attr>
        </path>
        <path android:pathData="M1172.6 932L893.2 524.8c-53.3 36.7-104 76.6-151.7 119.6l330.1 367.2c31.7-28.6 65.5-55.2 101-79.6zm1092.2-13.1L2534 505.1c-54-35.1-110.3-66.7-168.4-94.6l-213 445.5c38.7 18.5 76.2 39.5 112.2 62.9zm-536.1 823.8l-212.3 444c19.4 9.3 39.3 17.3 59.8 24l152.5-468z" android:strokeAlpha="0.2" android:fillColor="#ffffff" android:fillAlpha="0.04"/>
        <path android:pathData="M1728.7 1742.7l412.5 268.4c11.7-18 22.2-36.7 31.5-56.1l-444-212.3zm223.1 438.8l222.4 437.5c38.6-19.6 75.5-41.5 110.6-65.6l-277.6-404.7c-17.6 12.1-36.1 23-55.4 32.8zm-59.2 25.3l163.4 462.8c40.9-14.4 80.3-31.3 118.2-50.6l-222.4-437.5c-19 9.7-38.7 18.1-59.2 25.3zm-316.4 3.9l-152.1 466.6c40.6 13.3 82.2 24 124.6 31.8l89.9-482.5c-21.3-3.9-42.1-9.2-62.4-15.9zm976.3 68.1l413.8 269.2c35.1-54 66.8-110.3 94.6-168.4l-445.5-213c-18.5 38.7-39.5 76.2-62.9 112.2zm-862-1026.8c-21.1 1.6-42.4 4.7-63.7 9.2l101.9 481.5 26.2-491.5c-21.2-1.1-42.7-0.9-64.4 0.8zm250.5 46.7c-19.4-9.3-39.3-17.3-59.8-24l-152.5 468 268.4-412.5c-18-11.7-36.7-22.2-56.1-31.5z" android:strokeAlpha="0.2" android:fillColor="#ffffff" android:fillAlpha="0.04"/>
        <path android:pathData="M1037.8 397.8c811.5-429.5 1778.8-175.3 2160.7 567.8 381.8 743.1 33.6 1693.7-777.9 2123.2-811.5 429.5-1778.8 175.3-2160.7-567.8-381.8-743.1-33.5-1693.6 777.9-2123.2z">
            <aapt:attr name="android:fillColor">
                <gradient android:startX="313" android:startY="2657.6" android:endX="3168.3" android:endY="1026" android:type="linear">
                    <item android:offset="0" android:color="#19FF1371"/>
                    <item android:offset="0.6" android:color="#66A701E0"/>
                    <item android:offset="0.9" android:color="#668F00E7"/>
                </gradient>
            </aapt:attr>
        </path>
        <path android:pathData="M1460.3 2155.2c18 11.7 36.7 22.3 56.1 31.5 19.4 9.3 39.3 17.3 59.8 24l-152.1 466.6c-40.9-13.3-80.7-29.4-119.3-47.8-38.7-18.6-76.2-39.6-112.1-63l267.6-411.3zm1092.2 123.6c-23.3 35.9-49.1 70.2-77 102.9l-372.8-319c13.9-16.4 26.8-33.6 38.5-51.5l411.3 267.6zm63-112.2c-18.6 38.7-39.6 76.2-63 112.2l-411.3-267.7c11.7-17.9 22.3-36.7 31.5-56.1l442.8 211.6zm-1292.7-145.4c12.2 17.7 25.5 34.6 39.8 50.5l-365 328.1c-28.6-31.7-55.2-65.4-79.5-101l404.7-277.6zm1385.9-354.8c3.4 43.3 3.9 86.2 1.6 128.6l-490-26.1c1.1-21.2 0.8-42.7-0.9-64.4l489.3-38.1zm-1461.5 178.2l481.5-101.9-464.1 163.9L801.8 2070c-14-39.9-25.7-81.2-34.7-123.8l480.1-101.6zm11.7 45c0.4 1.2 0.8 2.5 1.2 3.8-0.4-1.3-0.8-2.6-1.2-3.8zm-3.4-11.4c0.2 0.6 0.4 1.2 0.5 1.8-0.1-0.6-0.3-1.2-0.5-1.8zm-4.7-17.7c0.7 2.6 1.3 5.2 2 7.8-0.3-1.3-0.7-2.6-1-3.9-0.3-1.3-0.7-2.6-1-3.9zm-13.7-144c1.2-21.6 3.7-42.9 7.6-63.9l484 90.1-491.6-26.2c-1.1 21.3-0.8 42.8 0.9 64.4L748.7 1819c-3.4-43.2-3.9-86.2-1.6-128.6l490 26.1zm1418.5-301.1c14 40 25.7 81.3 34.7 123.8l-480.1 101.6c-4.5-21.3-10.3-42-17.4-62l462.8-163.4zm-116.3-228.8c24.1 35.1 46.1 72.1 65.7 110.6l-437.5 222.4c-9.8-19.3-20.8-37.8-32.9-55.4l404.7-277.6zm-1254.6 343.8c-9.3 19.4-17.3 39.3-24 59.8-6.6 20.3-12 41.2-15.9 62.4l-482.5-89.8c7.9-42.5 18.5-84.1 31.8-124.7 13.3-40.8 29.4-80.7 47.9-119.3l442.7 211.6zm748.6-722.3c40.9 13.3 80.7 29.4 119.3 47.9 38.7 18.5 76.2 39.5 112.2 62.9l-267.7 411.3c-18-11.7-36.7-22.2-56.1-31.5s-39.3-17.3-59.8-24l152.1-466.6zm-678.6 614.6v0.1c-13.9 16.3-26.9 33.5-38.5 51.5l-411.4-267.6c23.4-36 49.2-70.3 77.1-103l372.8 319zm95.5-85.9c-17.8 12.2-34.7 25.5-50.5 39.8l-328.1-365c31.7-28.6 65.4-55.1 101-79.5l277.6 404.7zm202.2-574.1c43.3-3.4 86.2-3.9 128.6-1.7l-26.1 490.1c-21.2-1.1-42.8-0.9-64.4 0.8l-38.1-489.2zm-127.2 18.4c42.6-9 85-15 127.2-18.4l38.1 489.3c-21.1 1.6-42.4 4.7-63.7 9.2l-101.6-480.1z" android:fillAlpha="0.1">
            <aapt:attr name="android:fillColor">
                <gradient android:centerX="1727.8" android:centerY="1744.4" android:gradientRadius="981.4" android:type="radial">
                    <item android:offset="0.5" android:color="#00FFFFFF"/>
                    <item android:offset="1" android:color="#FFFFFFFF"/>
                </gradient>
            </aapt:attr>
        </path>
        <path android:pathData="M1316.2 1474.3l-411.3-267.6c-23.4 35.9-44.4 73.4-62.9 112.1l442.7 211.6c9.3-19.3 19.8-38.1 31.5-56.1zm-71.4 178.3l-482.6-89.8c-7.8 41.8-12.9 84.5-15.2 127.6l490.1 26.1c1.2-21.6 3.7-42.9 7.7-63.9zm163.9 464.1l-319 372.8c32.7 27.9 67 53.7 102.9 77l267.7-411.3c-18-11.7-35.2-24.6-51.6-38.5zm758.8-597.1c-9.8-19.3-20.8-37.8-32.9-55.4l-405.9 278.5 438.8-223.1z" android:fillColor="#ffffff" android:fillAlpha="0.15"/>
        <path android:pathData="M1728.7 1742.7l152.5-468c-20.3-6.7-41.1-12-62.4-16l-90.1 484z" android:fillColor="#ffffff" android:fillAlpha="0.15"/>
        <path android:pathData="M1728.7 1742.7l90.1-483.9c-21-3.9-42.3-6.5-63.9-7.6l-26.2 491.5zm366.1-329c-14.4-16.1-29.8-31-46.2-45l-319.9 374 366.1-329.1v0.1z" android:fillColor="#ffffff" android:fillAlpha="0.15"/>
        <path android:pathData="M1728.7 1742.7l405.9-278.5c-12.2-17.7-25.5-34.6-39.8-50.5l-366.1 329z" android:fillColor="#ffffff" android:fillAlpha="0.15"/>
        <path android:pathData="M1728.7 1742.7l481.5-101.9c-4.5-21.3-10.3-42-17.4-62l-464.1 163.9z" android:fillColor="#ffffff" android:fillAlpha="0.15"/>
        <path android:pathData="M1728.7 1742.7l223.1 438.8c19.3-9.8 37.8-20.8 55.4-32.9l-278.5-405.9zm163.9 464.1c20.5-7.2 40.2-15.6 59.2-25.3l-223.1-438.8 163.9 464.1zm-163.9-464.1l-152.5 468c20.3 6.7 41.2 12 62.4 16l90.1-484zm0 0l38.2 490.7c21.1-1.6 42.4-4.7 63.7-9.2l-101.9-481.5z" android:fillColor="#ffffff" android:fillAlpha="0.15"/>
        <path android:pathData="M1728.7 1742.7l491.6 26.2c1.1-21.3 0.8-42.7-0.9-64.4l-490.7 38.2zm374 320c13.9-16.4 26.8-33.6 38.5-51.5l-412.4-268.4 373.9 319.9zm-374-320l-444-212.3c-9.3 19.4-17.3 39.3-24 59.8l468 152.5zm-412.5-268.4c-11.7 18-22.2 36.8-31.5 56.1l444 212.3-412.5-268.4z" android:fillColor="#ffffff" android:fillAlpha="0.15"/>
        <path android:pathData="M1728.7 1742.7l-374-320c-13.9 16.4-26.8 33.6-38.5 51.6l412.5 268.4zm0 0l-468-152.5c-6.6 20.3-12 41.2-15.9 62.4l483.9 90.1zm0 0l-319.9 374c16.3 13.9 33.5 26.8 51.5 38.5l268.4-412.5zm0 0l-490.7 38.2c1.6 21.1 4.7 42.4 9.2 63.7l481.5-101.9z" android:fillColor="#ffffff" android:fillAlpha="0.15"/>
        <path android:pathData="M1728.7 1742.7l-491.5-26.2c-1.2 21.3-0.9 42.8 0.8 64.4l490.7-38.2zm-1122-959.9c-41.9 49-80.5 100.7-115.6 154.6-35.1 54-66.7 110.3-94.6 168.5L842 1318.8c18.5-38.7 39.5-76.2 62.9-112.1 23.4-35.9 49.1-70.3 77-103L606.7 782.8zM2605 1297.2l440.3-223.8c-29.4-57.9-62.4-113.4-98.7-166.2l-407.2 279.4c24.1 35.1 46 72.1 65.6 110.6zm85.3 242l483-102.2c-13.6-63.9-31-126-52.2-186l-465.5 164.4c14 40 25.7 81.3 34.7 123.8zm-150.9-352.6l407.2-279.4c-36.7-53.3-76.6-104-119.5-151.7l-367.3 330.1c28.6 31.7 55.2 65.5 79.6 101zM1805 2722.7l38.3 492.2c63.4-5 127.2-14.1 191.1-27.7l-102.2-482.9c-42.5 9-85 15-127.2 18.4zm670.5-341l375.2 320.9c41.9-49 80.5-100.7 115.6-154.6l-413.8-269.2c-23.3 35.9-49.1 70.2-77 102.8v0.1zM2056 2669.6l164.4 465.5c61.5-21.6 120.7-47 177.6-75.9L2174.2 2619c-37.8 19.2-77.3 36.2-118.2 50.5v0.1z" android:fillColor="#ffffff" android:fillAlpha="0.15"/>
        <path android:pathData="M2564.2 2960.6c-52.8 36.3-108.2 69.3-166.2 98.7L2174.2 2619c38.6-19.6 75.5-41.5 110.7-65.6l279.3 407.2zm-1140.1-283.2c40.6 13.2 82.2 23.8 124.6 31.8l-90.4 485.4c-63.6-11.8-126.2-27.9-187.2-47.8l153-469.4zm-334.3-187.9c32.6 27.9 67 53.7 102.9 77v0.1c35.9 23.4 73.4 44.3 112.1 62.9L1091.9 3075c-58.2-27.9-114.4-59.5-168.4-94.6-54-35.2-105.7-73.8-154.7-115.7l321-375.2zm334.3 187.9v-0.1 0.1zM918 2298.8c24.4 35.5 51 69.3 79.6 101l-367.2 330.1c-43-47.7-82.9-98.3-119.6-151.7L918 2298.9v-0.1zm2282.9-670.7c5.2 65 6 129.5 2.6 193.2l-493.1-26.3c2.2-42.4 1.7-85.4-1.7-128.6l492.2-38.3zM842 1318.8c-18.5 38.6-34.5 78.4-47.9 119.3-13.3 40.6-23.9 82.2-31.8 124.6-7.8 41.9-13 84.6-15.2 127.7-2.3 42.4-1.8 85.4 1.6 128.6 3.4 42.2 9.4 84.7 18.4 127.2 9 42.6 20.7 83.9 34.7 123.8l-465.5 164.4c-21.1-60-38.6-122.1-52.1-186-13.6-63.9-22.7-127.7-27.7-191.1-5.2-64.9-6-129.4-2.6-193.2 3.4-64.8 11.1-128.9 22.9-191.8 11.8-63.6 27.9-126.2 47.8-187.2 20.1-61.4 44.1-121.3 71.9-179.2v-0.1l445.5 213zm1846.7-698.1c48.9 41.8 95.1 86.8 138.4 134.8l-367.3 330.1-365 328.1c-14.4-16.1-29.8-31-46.1-45l319-372.8 321-375.2zM1423 298.2c63.9-13.6 127.7-22.7 191.1-27.7 65-5.2 129.5-6 193.2-2.6 64.8 3.4 128.9 11.1 191.8 22.9 63.7 11.8 126.2 27.9 187.2 47.8 61.5 20.1 121.3 44.1 179.3 71.9l-213 445.5c-38.6-18.5-78.4-34.5-119.3-47.9-40.6-13.3-82.2-23.9-124.6-31.8-41.9-7.8-84.5-13-127.7-15.2-42.4-2.3-85.4-1.8-128.6 1.6-42.2 3.4-84.6 9.4-127.2 18.4L1423 298.2zm93.4 1888.5c-19.3-9.2-38.1-19.7-56.1-31.5l268.4-412.5-212.3 444zm-153.8-115c-14.3-15.9-27.6-32.8-39.8-50.5l405.9-278.5-366.1 329zm366.1-329v-0.1 0.1zm0-0.1l-329-366c15.9-14.3 32.8-27.6 50.5-39.8l278.5 405.8zm38.2 490.8c21.1-1.6 42.4-4.7 63.7-9.2l101.6 480.1c-42.5 9-85 15.1-127.2 18.4l-38.1-489.3zm693.3-1147.5c28.6 31.7 55.2 65.4 79.6 101l-404.7 277.6c-12.2-17.8-25.6-34.7-39.9-50.6l365-328z" android:strokeAlpha="0.25" android:fillAlpha="0.25">
            <aapt:attr name="android:fillColor">
                <gradient android:centerX="1717.4" android:centerY="1719.4" android:gradientRadius="1451.4" android:type="radial">
                    <item android:offset="0.7" android:color="#00FFFFFF"/>
                    <item android:offset="1" android:color="#7FFFFFFF"/>
                </gradient>
            </aapt:attr>
        </path>
        <path android:pathData="M1172.6 932L893.2 524.8c-53.3 36.7-104 76.6-151.7 119.6l330.1 367.2c31.7-28.6 65.5-55.2 101-79.6zm1092.2-13.1L2534 505.1c-54-35.1-110.3-66.7-168.4-94.6l-213 445.5c38.7 18.5 76.2 39.5 112.2 62.9zm-536.1 823.8l-212.3 444c19.4 9.3 39.3 17.3 59.8 24l152.5-468z" android:strokeAlpha="0.2" android:fillColor="#ffffff" android:fillAlpha="0.04"/>
        <path android:pathData="M1728.7 1742.7l412.5 268.4c11.7-18 22.2-36.7 31.5-56.1l-444-212.3zm223.1 438.8l222.4 437.5c38.6-19.6 75.5-41.5 110.6-65.6l-277.6-404.7c-17.6 12.1-36.1 23-55.4 32.8zm-59.2 25.3l163.4 462.8c40.9-14.4 80.3-31.3 118.2-50.6l-222.4-437.5c-19 9.7-38.7 18.1-59.2 25.3zm-316.4 3.9l-152.1 466.6c40.6 13.3 82.2 24 124.6 31.8l89.9-482.5c-21.3-3.9-42.1-9.2-62.4-15.9zm976.3 68.1l413.8 269.2c35.1-54 66.8-110.3 94.6-168.4l-445.5-213c-18.5 38.7-39.5 76.2-62.9 112.2zm-862-1026.8c-21.1 1.6-42.4 4.7-63.7 9.2l101.9 481.5 26.2-491.5c-21.2-1.1-42.7-0.9-64.4 0.8zm250.5 46.7c-19.4-9.3-39.3-17.3-59.8-24l-152.5 468 268.4-412.5c-18-11.7-36.7-22.2-56.1-31.5z" android:strokeAlpha="0.2" android:fillColor="#ffffff" android:fillAlpha="0.04"/>
    </group>
</vector>
